wildered/__init__.py
wildered/ast/__init__.py
wildered/ast/directive_parser.py
wildered/ast/source_code.py
wildered/ast/utils.py
wildered/context/__init__.py
wildered/context/autocomplete.py
wildered/context/cli/__init__.py
wildered/context/cli/cli.py
wildered/context/commands/__init__.py
wildered/context/commands/scan.py
wildered/context/decorator.py
wildered/context/dependency.py
wildered/context/directives.py
wildered/context/prompts/coder.md
wildered/context/prompts/write_test.md
wildered/context/prompts.py
wildered/context/tasks.py
wildered/context/utils.py
wildered/cst/__init__.py
wildered/cst/directive_parser.py
wildered/cst/source_code.py
wildered/cst/utils.py
wildered/directive.py
wildered/group.py
wildered/logger.py
wildered/models.py
wildered/utils.py
wildered-0.2.4.dist-info/entry_points.txt
wildered-0.2.4.dist-info/LICENSE.md
wildered-0.2.4.dist-info/METADATA
wildered-0.2.4.dist-info/WHEEL
wildered-0.2.4.dist-info/RECORD
