Metadata-Version: 2.1
Name: wildered
Version: 0.2.4
Summary: 
Home-page: https://github.com/outday29/wildered
License: MIT
Author: engkheng
Author-email: ongengkheng929@gmail.com
Requires-Python: >=3.10,<4.0
Classifier: License :: OSI Approved :: MIT License
Classifier: Programming Language :: Python :: 3
Classifier: Programming Language :: Python :: 3.10
Classifier: Programming Language :: Python :: 3.11
Classifier: Programming Language :: Python :: 3.12
Requires-Dist: ast-comments (>=1.0.1,<2.0.0)
Requires-Dist: chardet (>=5.2.0,<6.0.0)
Requires-Dist: guidance (>=0.1.10,<0.2.0)
Requires-Dist: jinja2 (>=3.1.2,<4.0.0)
Requires-Dist: langchain (>=0.0.198,<0.0.199)
Requires-Dist: libcst (>=1.0.0,<2.0.0)
Requires-Dist: loguru (>=0.7.0,<0.8.0)
Requires-Dist: pydantic (>=1.10.8,<2.0.0)
Requires-Dist: pyperclip (>=1.8.2,<2.0.0)
Requires-Dist: typer (>=0.9.0,<0.10.0)
Requires-Dist: wander (>=0.1.0,<0.2.0)
Project-URL: Repository, https://github.com/outday29/wildered
